traitkeyless/__init__.py
traitkeyless/keyless.py
traitkeyless/keyless.pyi
traitkeyless/py.typed
traitkeyless/ss58.py
traitkeyless/ss58.pyi
traitkeyless-0.1.4.dist-info/METADATA
traitkeyless-0.1.4.dist-info/WHEEL
traitkeyless-0.1.4.dist-info/top_level.txt
traitkeyless-0.1.4.dist-info/RECORD
