Metadata-Version: 2.1
Name: traitkeyless
Version: 0.1.4
Summary: This library provides functions for encoding and decoding keyless addresses, used by the TRAIT blockchain: application agent addresses, transactional addresses, and named addresses.
Author-email: Trait Tech PTE LTD <info@trait.tech>
License: Apache-2.0
Project-URL: Homepage, https://trait.tech
Project-URL: Repository, https://github.com/traittech/trait-keyless.git
Project-URL: Issues, https://github.com/traittech/trait-keyless/issues
Classifier: Development Status :: 4 - Beta
Classifier: Intended Audience :: Developers
Classifier: Programming Language :: Python :: 3
Classifier: License :: OSI Approved :: Apache Software License
Classifier: Operating System :: OS Independent
Requires-Python: >=3.12
Requires-Dist: base58<3,>=1.0.3
